flipflop.v
module flipflop(
    input   wire    clk,
    input   wire    in0,
    output  wire    out0
);

reg ff;

initial begin
    ff = 2'b0;
end

always @ (posedge clk)
begin
    ff <= in0;
end

assign out0 = ff;

endmodule

flipflop_testbench.v
// iverilog.exe -o .\flipflop_testbench -s flipflop_testbench .\flipflop_testbench.v .\flipflop.v
module flipflop_testbench();

reg clock;
reg in0;
wire out0;

flipflop ff_ins0(clock, in0, out0);

initial begin
    in0 = 0;
    clock = 0;

    $dumpfile("flipflop_testbench.vcd"); // value change dump.
    $dumpvars(0, flipflop_testbench);
end

always #10 clock = ~clock;

initial begin
    #10 in0 = 2'b0;
    #10 in0 = 2'b1;
    #20 in0 = 2'b0;
    #20 in0 = 2'b1;
    #30 in0 = 2'b0;
    #30 in0 = 2'b1;
    #10 $finish;
end


endmodule

flipflop_testbench.vcd
$date
	Thu May 05 22:22:56 2022
$end
$version
	Icarus Verilog
$end
$timescale
	1s
$end
$scope module flipflop_testbench $end
$var wire 1 ! out0 $end
$var reg 1 " clock $end
$var reg 1 # in0 $end
$scope module ff_ins0 $end
$var wire 1 " clk $end
$var wire 1 # in0 $end
$var wire 1 ! out0 $end
$var reg 1 $ ff $end
$upscope $end
$upscope $end
$enddefinitions $end
#0
$dumpvars
0$
0#
0"
0!
$end
#10
1"
#20
1#
0"
#30
1!
1$
1"
#40
0"
0#
#50
0!
0$
1"
#60
0"
1#
#70
1!
1$
1"
#80
0"
#90
0!
0$
1"
0#
#100
0"
#110
1"
#120
0"
1#
#130
1!
1$
1"
