selector.v
module selector(
    input wire in0,
    input wire in1,
    input wire sel0,
    output wire out0
);

assign out0 = sel0 ? in1 : in0;

endmodule

selector_testbench.v
// iverilog.exe -o .\selector_testbench -s selector_testbench .\selector_testbench.v .\selector.v
module selector_testbench();

reg in0;
reg in1;
reg sel0;
wire out1;

selector selector_inst0(in0, in1, sel0, out1);

initial begin
    $dumpfile("selector_testbench.vcd");
    $dumpvars(0, selector_testbench);

        in0 = 0;    in1 = 0;    sel0 = 0;
    #10 in0 = 0;    in1 = 0;    sel0 = 1;
    #10 in0 = 0;    in1 = 1;    sel0 = 0;
    #10 in0 = 0;    in1 = 1;    sel0 = 1;
    #10 in0 = 1;    in1 = 0;    sel0 = 0;
    #10 in0 = 1;    in1 = 0;    sel0 = 1;
    #10 in0 = 1;    in1 = 1;    sel0 = 0;
    #10 in0 = 1;    in1 = 1;    sel0 = 1;

    #10 $finish;
end

endmodule

selector_testbench.vcd
$date
	Thu May 05 16:28:31 2022
$end
$version
	Icarus Verilog
$end
$timescale
	1s
$end
$scope module selector_testbench $end
$var wire 1 ! out1 $end
$var reg 1 " in0 $end
$var reg 1 # in1 $end
$var reg 1 $ sel0 $end
$scope module selector_inst0 $end
$var wire 1 " in0 $end
$var wire 1 # in1 $end
$var wire 1 $ sel0 $end
$var wire 1 ! out0 $end
$upscope $end
$upscope $end
$enddefinitions $end
#0
$dumpvars
0$
0#
0"
0!
$end
#10
1$
#20
0$
1#
#30
1!
1$
#40
0$
0#
1"
#50
0!
1$
#60
1!
0$
1#
#70
1$
